nt_pygrambot/__init__.py
nt_pygrambot/dispatcher.py
nt_pygrambot/handlers.py
nt_pygrambot/types.py
nt_pygrambot/updater.py
nt_pygrambot-0.1.0.dist-info/licenses/LICENSE
nt_pygrambot-0.1.0.dist-info/METADATA
nt_pygrambot-0.1.0.dist-info/WHEEL
nt_pygrambot-0.1.0.dist-info/top_level.txt
nt_pygrambot-0.1.0.dist-info/RECORD
