Metadata-Version: 2.4
Name: nt_pygrambot
Version: 0.1.0
Summary: Python Telegram Bot
Home-page: https://github.com/ziyocamp/py-gram-bot/pygrambot
Author: SN01
Classifier: Programming Language :: Python :: 3
Classifier: License :: OSI Approved :: MIT License
Classifier: Operating System :: OS Independent
Requires-Python: >=3.9
License-File: LICENSE
Dynamic: author
Dynamic: classifier
Dynamic: description
Dynamic: description-content-type
Dynamic: home-page
Dynamic: license-file
Dynamic: requires-python
Dynamic: summary
